ConfigAutomation/Baseline/attachment/A-Roadmap-to-Success-scorm.zip
ConfigAutomation/Baseline/attachment/Fire-Drills-Procedures.pdf
ConfigAutomation/Baseline/attachment/Sample.jpg
ConfigAutomation/Baseline/attachment/TestAttachment.txt
ConfigAutomation/Baseline/src/ConfigFileNames.py
ConfigAutomation/Baseline/src/CreateDirectories.py
ConfigAutomation/Baseline/src/DoConfig.py
ConfigAutomation/Baseline/src/Sheet2ScriptMapping.py
ConfigAutomation/Baseline/src/utils.py
ConfigAutomation/Baseline/src/ERP/AP/APSequences
ConfigAutomation/Baseline/src/ERP/AP/Manage DFF Values.py
ConfigAutomation/Baseline/src/ERP/AP/ManageAgingPeriods.py
ConfigAutomation/Baseline/src/ERP/AP/ManageCommonOptionsforPayablesandProcurement.py
ConfigAutomation/Baseline/src/ERP/AP/ManageDisbursementSystemOptions.py
ConfigAutomation/Baseline/src/ERP/AP/ManageDistributionSets.py
ConfigAutomation/Baseline/src/ERP/AP/ManageFormats.py
ConfigAutomation/Baseline/src/ERP/AP/ManageInvoiceHoldsandReleases.py
ConfigAutomation/Baseline/src/ERP/AP/ManageInvoiceOptions.py
ConfigAutomation/Baseline/src/ERP/AP/ManageInvoiceTolerances.py
ConfigAutomation/Baseline/src/ERP/AP/ManagePayablesCalendars.py
ConfigAutomation/Baseline/src/ERP/AP/ManagePayablesDescriptiveFlexfields.py
ConfigAutomation/Baseline/src/ERP/AP/ManagePayablesDocumentSequences.py
ConfigAutomation/Baseline/src/ERP/AP/ManagePayablesLookups.py
ConfigAutomation/Baseline/src/ERP/AP/ManagePaymentMethodDefaultingRules.py
ConfigAutomation/Baseline/src/ERP/AP/ManagePaymentMethods.py
ConfigAutomation/Baseline/src/ERP/AP/ManagePaymentOptions.py
ConfigAutomation/Baseline/src/ERP/AP/ManagePaymentSystems.py
ConfigAutomation/Baseline/src/ERP/AP/ManagePaymentTerms.py
ConfigAutomation/Baseline/src/ERP/AP/ManageTransmissionConfigurations.py
ConfigAutomation/Baseline/src/ERP/AP/PaymentProcess Profiles.py
ConfigAutomation/Baseline/src/ERP/AP/SpecifySupplierNumbering.py
ConfigAutomation/Baseline/src/ERP/AR/AR Sequence
configautomation-0.0.7.dist-info/METADATA
configautomation-0.0.7.dist-info/WHEEL
configautomation-0.0.7.dist-info/licenses/LICENSE.txt
configautomation-0.0.7.dist-info/RECORD
