Metadata-Version: 2.4
Name: ConfigAutomation
Version: 0.0.7
Summary: Configuration Automation scripts for Oracle Cloud Applications
Project-URL: Homepage, https://github.com/dharmendra-ds/ConfigAutomation
Author-email: Drivestream <dharmendra.mirapakayala@drivestream.com>
License-File: LICENSE.txt
Classifier: License :: OSI Approved :: MIT License
Classifier: Operating System :: OS Independent
Classifier: Programming Language :: Python :: 3
Requires-Python: >=3.8
